django_epfl_entra_id-0.0.8.dist-info/METADATA
django_epfl_entra_id-0.0.8.dist-info/WHEEL
django_epfl_entra_id-0.0.8.dist-info/entry_points.txt
django_epfl_entra_id-0.0.8.dist-info/licenses/LICENSE
django_epfl_entra_id/__init__.py
django_epfl_entra_id/auth.py
django_epfl_entra_id/urls.py
django_epfl_entra_id/views.py
tests/__init__.py
tests/settings.py
tests/test_profile_auth.py
tests/test_user_auth.py
tests/test_views.py
tests/urls.py
tests/user/__init__.py
tests/user/migrations/0001_initial.py
tests/user/migrations/__init__.py
tests/user/models.py
tests/userprofile/__init__.py
tests/userprofile/migrations/0001_initial.py
tests/userprofile/migrations/__init__.py
tests/userprofile/models.py
django_epfl_entra_id-0.0.8.dist-info/RECORD
