Metadata-Version: 2.1
Name: django-epfl-entra-id
Version: 0.0.8
Summary: Custom Microsoft Entra ID Authentication Backend for Django.
Keywords: django,entraid,oidc,authentication
Author-Email: Lindo Duratti <lindo.duratti@epfl.ch>, William Belle <william.belle@gmail.com>
License: MIT
Classifier: Environment :: Web Environment
Classifier: Framework :: Django
Classifier: Framework :: Django :: 1.11
Classifier: Framework :: Django :: 2.2
Classifier: Framework :: Django :: 3.2
Classifier: Framework :: Django :: 4.2
Classifier: Framework :: Django :: 5.2
Classifier: Intended Audience :: Developers
Classifier: Operating System :: OS Independent
Classifier: Programming Language :: Python
Classifier: Programming Language :: Python :: 3
Classifier: Programming Language :: Python :: 3.6
Classifier: Programming Language :: Python :: 3.7
Classifier: Programming Language :: Python :: 3.8
Classifier: Programming Language :: Python :: 3.9
Classifier: Programming Language :: Python :: 3.10
Classifier: Programming Language :: Python :: 3.11
Classifier: Programming Language :: Python :: 3.12
Classifier: Programming Language :: Python :: 3.13
Classifier: Programming Language :: Python :: 3.14
Classifier: Topic :: Internet :: WWW/HTTP
Classifier: Topic :: System :: Systems Administration :: Authentication/Directory
Project-URL: Homepage, https://github.com/epfl-si/django-epfl-entra-id
Project-URL: Source, https://github.com/epfl-si/django-epfl-entra-id
Project-URL: Tracker, https://github.com/epfl-si/django-epfl-entra-id/issues
Project-URL: Changelog, https://github.com/epfl-si/django-epfl-entra-id/blob/main/CHANGELOG.md
Requires-Python: >=3.6
Requires-Dist: mozilla-django-oidc<5
Requires-Dist: pyjwt
